notion_cli/__init__.py
notion_cli/notion_api.py
notion_cli-0.1.0.dist-info/METADATA
notion_cli-0.1.0.dist-info/WHEEL
notion_cli-0.1.0.dist-info/entry_points.txt
notion_cli-0.1.0.dist-info/top_level.txt
notion_cli-0.1.0.dist-info/RECORD
