Metadata-Version: 2.1
Name: notion-cli
Version: 0.1.0
Summary: A CLI tool to update Notion tasks utilising the Notion API
Author: Rao Abdul
Author-email: raoabdulhadi952@gmail.com
Classifier: Programming Language :: Python :: 3
Classifier: License :: OSI Approved :: MIT License
Classifier: Operating System :: OS Independent
Requires-Python: >=3.6
Requires-Dist: notion-client
Requires-Dist: click
Requires-Dist: rich
